everything/__init__.py
import_everything-0.0.1.dist-info/LICENSE
import_everything-0.0.1.dist-info/METADATA
import_everything-0.0.1.dist-info/WHEEL
import_everything-0.0.1.dist-info/top_level.txt
import_everything-0.0.1.dist-info/RECORD
